LICENSE
MANIFEST.in
README.md
setup.py
blockscout_python.egg-info/PKG-INFO
blockscout_python.egg-info/SOURCES.txt
blockscout_python.egg-info/dependency_links.txt
blockscout_python.egg-info/not-zip-safe
blockscout_python.egg-info/requires.txt
blockscout_python.egg-info/top_level.txt
python/prod/__init__.py
python/prod/configs/ARBITRUM-REST-stable.json
python/prod/configs/ARBITRUM-RPC-stable.json
python/prod/configs/ETHEREUM-REST-stable.json
python/prod/configs/ETHEREUM-RPC-stable.json
python/prod/configs/OPTIMISM-REST-stable.json
python/prod/configs/OPTIMISM-RPC-stable.json
python/prod/configs/POLYGON-REST-stable.json
python/prod/configs/POLYGON-RPC-stable.json
python/prod/configs/ROLLUX-REST-stable.json
python/prod/configs/ROLLUX-RPC-stable.json
python/prod/configs/__init__.py
python/prod/cull/__init__.py
python/prod/cull/coin_transfers.py
python/prod/cull/data_dictionary.py
python/prod/cull/token_transfers.py
python/prod/enums/__init__.py
python/prod/enums/actions_enum.py
python/prod/enums/api_enum.py
python/prod/enums/delimiters_enum.py
python/prod/enums/explorers_enum.py
python/prod/enums/fields_enum.py
python/prod/enums/modules_enum.py
python/prod/enums/nets_enum.py
python/prod/enums/rest_fields_enum.py
python/prod/enums/rest_filters_enum.py
python/prod/enums/rpc_fields_enum.py
python/prod/enums/tags_enum.py
python/prod/explorer/__init__.py
python/prod/explorer/blockscout.py
python/prod/modules/__init__.py
python/prod/modules/rest_accounts.py
python/prod/modules/rest_blocks.py
python/prod/modules/rest_contracts.py
python/prod/modules/rest_stats.py
python/prod/modules/rest_tokens.py
python/prod/modules/rest_transactions.py
python/prod/modules/rpc_accounts.py
python/prod/modules/rpc_blocks.py
python/prod/modules/rpc_contracts.py
python/prod/modules/rpc_stats.py
python/prod/modules/rpc_tokens.py
python/prod/modules/rpc_transactions.py
python/prod/utils/__init__.py
python/prod/utils/conversions.py
python/prod/utils/parsing.py