Metadata-Version: 2.1
Name: blockscout-python
Version: 0.1.2
Summary: Python API for blockscout.com explorers
Home-page: https://github.com/defipy-devs
Author: icmoore
Author-email: defipy.devs@gmail.com
License: MIT
License-File: LICENSE
Requires-Dist: requests
